{
    "$schema": "https://schema.management.azure.com/schemas/2019-04-01/deploymentTemplate.json#",
    "contentVersion": "1.0.0.0",
    "parameters": {
        "virtualNetworkName": {
            "type": "string",
            "metadata": {
                "description": "Name of virtual network"
            }
        }
    },
    "functions": [],
    "variables": {},
    "resources": [
        {
            "name": "[parameters('virtualNetworkName')]",
            "type": "Microsoft.Network/virtualNetworks",
            "apiVersion": "2019-11-01",
            "location": "[resourceGroup().location]",
            "tags": {
                "displayName": "[parameters('virtualNetworkName')]"
            },
            "properties": {
                "addressSpace": {
                    "addressPrefixes": [
                        "10.0.0.0/16"
                    ]
                },
                "subnets": [
                    {
                        "name": "subnet-1",
                        "properties": {
                            "addressPrefix": "10.0.0.0/24"
                        }
                    },
                    {
                        "name": "subnet-2",
                        "properties": {
                            "addressPrefix": "10.0.1.0/24"
                        }
                    }
                ]
            }
        }
    ],
    "outputs": {}
}